simple_soundboard/config.json
simple_soundboard/index.html
simple_soundboard/mqtt_api.py
simple_soundboard/sound_engine.py
simple_soundboard/static/img/wood.jpg
simple_soundboard/static/simple_soundboard/web_ui.js
simple_soundboard/web_ui.py
simple_soundboard-1.0.5.dist-info/METADATA
simple_soundboard-1.0.5.dist-info/entry_points.txt
simple_soundboard-1.0.5.dist-info/LICENSE
simple_soundboard-1.0.5.dist-info/WHEEL
simple_soundboard-1.0.5.dist-info/RECORD
