Metadata-Version: 2.1
Name: simple-soundboard
Version: 1.0.5
Summary: Simple Soundboard
License: Apache 2.0
Author: Martin Rioux
Requires-Python: >=3.9.0,<4.0.0
Classifier: License :: Other/Proprietary License
Classifier: Programming Language :: Python :: 3
Classifier: Programming Language :: Python :: 3.9
Classifier: Programming Language :: Python :: 3.10
Classifier: Programming Language :: Python :: 3.11
Classifier: Programming Language :: Python :: 3.9
Requires-Dist: fastapi (>=0.88.0,<0.89.0)
Requires-Dist: paho-mqtt (>=1.6.1,<2.0.0)
Requires-Dist: pygame (>=2.1.2,<3.0.0)
Requires-Dist: ujson (>=5.6.0,<6.0.0)
Requires-Dist: uvicorn (>=0.20.0,<0.21.0)
